[
	{
		"file": "D:\\stonekyu\\aquarium\\Source\\aquarium\\Mouse.cpp",
		"arguments": [
			"C:\\Program Files\\Microsoft Visual Studio\\2022\\Community\\VC\\Tools\\MSVC\\14.38.33130\\bin\\Hostx64\\x64\\cl.exe",
			"@D:\\stonekyu\\aquarium\\.vscode\\compileCommands_aquarium\\aquarium.1.rsp"
		],
		"directory": "C:\\Program Files\\Epic Games\\UE_5.4\\Engine\\Source"
	},
	{
		"file": "D:\\stonekyu\\aquarium\\Source\\aquarium\\Mouse.h",
		"arguments": [
			"C:\\Program Files\\Microsoft Visual Studio\\2022\\Community\\VC\\Tools\\MSVC\\14.38.33130\\bin\\Hostx64\\x64\\cl.exe",
			"@D:\\stonekyu\\aquarium\\.vscode\\compileCommands_aquarium\\aquarium.1.rsp"
		],
		"directory": "C:\\Program Files\\Epic Games\\UE_5.4\\Engine\\Source"
	},
	{
		"file": "D:\\stonekyu\\aquarium\\Source\\aquarium\\aquarium.Build.cs",
		"arguments": [
			"C:\\Program Files\\Microsoft Visual Studio\\2022\\Community\\VC\\Tools\\MSVC\\14.38.33130\\bin\\Hostx64\\x64\\cl.exe",
			"@D:\\stonekyu\\aquarium\\.vscode\\compileCommands_aquarium\\aquarium.1.rsp"
		],
		"directory": "C:\\Program Files\\Epic Games\\UE_5.4\\Engine\\Source"
	},
	{
		"file": "D:\\stonekyu\\aquarium\\Source\\aquarium\\aquarium.cpp",
		"arguments": [
			"C:\\Program Files\\Microsoft Visual Studio\\2022\\Community\\VC\\Tools\\MSVC\\14.38.33130\\bin\\Hostx64\\x64\\cl.exe",
			"@D:\\stonekyu\\aquarium\\.vscode\\compileCommands_aquarium\\aquarium.1.rsp"
		],
		"directory": "C:\\Program Files\\Epic Games\\UE_5.4\\Engine\\Source"
	},
	{
		"file": "D:\\stonekyu\\aquarium\\Source\\aquarium\\aquarium.h",
		"arguments": [
			"C:\\Program Files\\Microsoft Visual Studio\\2022\\Community\\VC\\Tools\\MSVC\\14.38.33130\\bin\\Hostx64\\x64\\cl.exe",
			"@D:\\stonekyu\\aquarium\\.vscode\\compileCommands_aquarium\\aquarium.1.rsp"
		],
		"directory": "C:\\Program Files\\Epic Games\\UE_5.4\\Engine\\Source"
	}
]